stablepy/__init__.py
stablepy/__version__.py
stablepy/diffusers_vanilla/adetailer.py
stablepy/diffusers_vanilla/constants.py
stablepy/diffusers_vanilla/extra_model_loaders.py
stablepy/diffusers_vanilla/extra_pipe/__init__.py
stablepy/diffusers_vanilla/extra_pipe/flux/__init__.py
stablepy/diffusers_vanilla/extra_pipe/flux/controlnet_flux.py
stablepy/diffusers_vanilla/extra_pipe/flux/pipeline_flux_controlnet.py
stablepy/diffusers_vanilla/extra_pipe/flux/pipeline_flux_img2img.py
stablepy/diffusers_vanilla/extra_pipe/flux/pipeline_flux_inpaint.py
stablepy/diffusers_vanilla/extra_pipe/sdxl/controlnet_union.py
stablepy/diffusers_vanilla/extra_pipe/sdxl/pipeline_controlnet_union_inpaint_sd_xl.py
stablepy/diffusers_vanilla/extra_pipe/sdxl/pipeline_controlnet_union_sd_xl.py
stablepy/diffusers_vanilla/extra_scheduler/__init__.py
stablepy/diffusers_vanilla/extra_scheduler/scheduling_dpmsolver_multistep.py
stablepy/diffusers_vanilla/extra_scheduler/scheduling_euler_discrete_variants.py
stablepy/diffusers_vanilla/extra_scheduler/scheduling_flow_match_dpmsolver_multistep.py
stablepy/diffusers_vanilla/high_resolution.py
stablepy/diffusers_vanilla/inpainting_canvas.py
stablepy/diffusers_vanilla/lora_loader.py
stablepy/diffusers_vanilla/main_prompt_embeds.py
stablepy/diffusers_vanilla/model.py
stablepy/diffusers_vanilla/multi_emphasis_prompt.py
stablepy/diffusers_vanilla/preprocessor/__init__.py
stablepy/diffusers_vanilla/preprocessor/constans_preprocessor.py
stablepy/diffusers_vanilla/preprocessor/controlnet_aux_beta/__init__.py
stablepy/diffusers_vanilla/preprocessor/controlnet_aux_beta/anyline/__init__.py
stablepy/diffusers_vanilla/preprocessor/controlnet_aux_beta/lineart_standard/__init__.py
stablepy/diffusers_vanilla/preprocessor/controlnet_aux_beta/preprocessor_utils.py
stablepy/diffusers_vanilla/preprocessor/controlnet_aux_beta/teed/Fsmish.py
stablepy/diffusers_vanilla/preprocessor/controlnet_aux_beta/teed/LICENSE.txt
stablepy-0.6.5.dist-info/LICENSE
stablepy-0.6.5.dist-info/METADATA
stablepy-0.6.5.dist-info/WHEEL
stablepy-0.6.5.dist-info/RECORD
