Metadata-Version: 2.1
Name: stablepy
Version: 0.6.5
Summary: A tool for easy use of stable diffusion
Author: Roger Condori(R3gm)
Author-email: rocondoriflores@gmail.com
Requires-Python: >=3.10,<4.0
Classifier: Programming Language :: Python :: 3
Classifier: Programming Language :: Python :: 3.10
Classifier: Programming Language :: Python :: 3.11
Classifier: Programming Language :: Python :: 3.12
Classifier: Programming Language :: Python :: 3.13
Requires-Dist: accelerate (==1.2.1)
Requires-Dist: compel (==2.0.2)
Requires-Dist: controlnet-aux (==0.0.6)
Requires-Dist: diffusers (==0.31.0)
Requires-Dist: facexlib (==0.3.0)
Requires-Dist: huggingface_hub (>=0.23.1)
Requires-Dist: insightface (>=0.7.3)
Requires-Dist: invisible-watermark (==0.2.0)
Requires-Dist: ipywidgets (==7.7.1)
Requires-Dist: lark
Requires-Dist: mediapipe (>=0.10.5)
Requires-Dist: mediapy (>=1.1.9)
Requires-Dist: numpy (<=1.26.4)
Requires-Dist: omegaconf (>=2.3.0)
Requires-Dist: onnxruntime (>=1.18.0)
Requires-Dist: opencv-contrib-python (>=4.8.0.76)
Requires-Dist: peft (>=0.11.1)
Requires-Dist: pytorch-lightning (>=2.0.9.post0)
Requires-Dist: safetensors (>=0.4.3)
Requires-Dist: sentencepiece
Requires-Dist: spandrel (==0.4.1)
Requires-Dist: spandrel-extra-arches (==0.2.0)
Requires-Dist: torch
Requires-Dist: torchaudio
Requires-Dist: torchsde (>=0.2.6)
Requires-Dist: torchvision
Requires-Dist: transformers (>=4.47.1,!=4.57.0)
Requires-Dist: ultralytics (<=8.3.48)
